RTL/defines.v
`define WIDTH 32

//Opcode for Instructions

// R-Type
`define R_op 6'b000000

// I-Type
`define lw_op   6'b100011 
`define sw_op   6'b101011
`define addi_op 6'b001000
`define andi_op 6'b001100
`define ori_op  6'b001101
`define slti_op 6'b001010
`define beq_op  6'b000100
`define bne_op  6'b000101

// J-Type
`define jump_op    6'b000010

// Function for R-type
`define add_funct 6'b100000
`define sub_funct 6'b100010
`define and_funct 6'b100100
`define or_funct  6'b100101
`define slt_funct 6'b101010
`define nor_funct 6'b100111
`define sll_funct 6'b000000
`define srl_funct 6'b000010

// ALUControl
`define EXE_ADD 4'b0000
`define EXE_AND 4'b0001
`define EXE_SUB 4'b0010
`define EXE_OR 4'b0011
`define EXE_SLT 4'b0100 
`define EXE_NOR 4'b0101 
`define EXE_SLL 4'b0110 
`define EXE_SRL 4'b0111 
`define EXE_NO_OPERATION 4'b1111

// Using for control 
`define R_control     7'b1000100
`define lw_control    7'b1101000
`define sw_control    7'b0011000
`define addi_control  7'b1001000
`define andi_control  7'b1001000
`define ori_control   7'b1001000
`define slti_control  7'b1001000
`define beq_control   7'b0000001
`define bne_control   7'b0000001
`define jump_control  7'b0000010

// Using for branch condition
`define beq 2'b11
`define bne 2'b01
`define not_branch 2'b00

RTL/Memory/IMEM.v
`include "defines.v"

module IMEM (
  input [`WIDTH-1:0] pc,
  output [`WIDTH-1:0] instr
);

  // Memory
  reg [`WIDTH-1:0] instr_memory [31:0];

  initial begin
    $readmemh("Verification/instrMem.txt", instr_memory);;
  end

  assign instr = instr_memory[pc[`WIDTH-1:2]]; // 4 byte aligned

endmodule

RTL/adder.v
`include "defines.v"

module adder(
  input [`WIDTH-1:0] a,
  input [`WIDTH-1:0] b,
  output [`WIDTH-1:0] sum
);
  assign sum = a + b;

endmodule

RTL/pc.v
`include "defines.v"

module pc(
  input clk, rst,
  input stall_pc,
  input [`WIDTH-1:0] pc_in,
  output reg [`WIDTH-1:0] pc_out
);

  always @(posedge clk) begin
    if(!rst) begin
      pc_out <= 0; // Reset the PC to 0
    end
    else if (stall_pc) begin
      pc_out <= pc_out; // Hold the value if stalled
    end
    else begin
      pc_out <= pc_in; // Update the PC with the new value
    end
  end

endmodule

RTL/mux2to1.v
`include "defines.v"

module mux2to1 #(parameter WIDTH = 32)(
  input [WIDTH-1:0] a,
  input [WIDTH-1:0] b,
  input sel,
  output [WIDTH-1:0] out
);
  assign out = (sel) ? b : a;
endmodule

RTL/pipeStages/IF.v
`include "defines.v"

module IFStage(
  input clk,
  input rst,
  input jump_decode, pcsrc_decode, stall_pc,
  input [`WIDTH-1:0] pc_branch, pc_jump,
  output [`WIDTH-1:0] pc_fetch, instr_fetch
);

  wire [`WIDTH-1:0] pc_in;
  wire [`WIDTH-1:0] pc_out_0, pc_out;

  // Select MUX
  mux2to1 select_branch(pc_fetch, pc_branch, pcsrc_decode, pc_out_0);
  mux2to1 select_jump(pc_out_0, pc_jump, jump_decode, pc_in);

  // PC
  pc pc(clk, rst, stall_pc, pc_in, pc_out);

  // Adder
  adder adder(pc_out, `WIDTH'b100, pc_fetch);

  IMEM imem (pc_out, instr_fetch);


endmodule

Verification/IF_tb.v
`timescale 1ns/1ps
`include "defines.v"

module IF_tb;

  // Inputs
  reg clk, rst;
  reg jump_decode, pcsrc_decode, stall_pc;
  reg [`WIDTH-1:0] pc_branch, pc_jump;

  // Outputs
  wire [`WIDTH-1:0] pc_fetch, instr_fetch;

  // Instantiate the IFStage module
  IFStage dut (
    .clk(clk),
    .rst(rst),
    .jump_decode(jump_decode),
    .pcsrc_decode(pcsrc_decode),
    .stall_pc(stall_pc),
    .pc_branch(pc_branch),
    .pc_jump(pc_jump),
    .pc_fetch(pc_fetch),
    .instr_fetch(instr_fetch)
  );

  // Clock generation: 10ns period
  initial begin
    clk = 0;
    forever #5 clk = ~clk;
  end

  // Monitor output
  always @(posedge clk) begin
    $display("Time %0t: pc_fetch = %h, instr_fetch = %h, jump = %b, branch = %b, stall = %b", 
              $time, pc_fetch, instr_fetch, jump_decode, pcsrc_decode, stall_pc);
  end

  // Stimulus
  initial begin
    $dumpfile("IF.vcd");
    $dumpvars(0, IF_tb);

    // Initial values
    rst = 1;
    jump_decode = 0;
    pcsrc_decode = 0;
    stall_pc = 0;
    pc_branch = 32'h00000000;
    pc_jump = 32'h00000000;

    // Apply reset
    #3 rst = 0;     // Reset active
    #10 rst = 1;    // Reset de-asserted

    // Normal PC increment
    #10;
    #10;

    // Stall PC
    stall_pc = 1;
    #10;
    stall_pc = 0;

    // Branch
    pcsrc_decode = 1;
    pc_branch = 32'h00000020;
    #10;
    pcsrc_decode = 0;

    // Jump
    jump_decode = 1;
    pc_jump = 32'h00000080;
    #10;
    jump_decode = 0;

    // End simulation
    #20;
    $finish;
  end

endmodule

IF.vcd
$date
	Sun May 18 18:37:43 2025
$end
$version
	Icarus Verilog
$end
$timescale
	1ps
$end
$scope module IF_tb $end
$var wire 32 ! pc_fetch [31:0] $end
$var wire 32 " instr_fetch [31:0] $end
$var reg 1 # clk $end
$var reg 1 $ jump_decode $end
$var reg 32 % pc_branch [31:0] $end
$var reg 32 & pc_jump [31:0] $end
$var reg 1 ' pcsrc_decode $end
$var reg 1 ( rst $end
$var reg 1 ) stall_pc $end
$scope module dut $end
$var wire 1 # clk $end
$var wire 1 $ jump_decode $end
$var wire 32 * pc_branch [31:0] $end
$var wire 32 + pc_jump [31:0] $end
$var wire 1 ' pcsrc_decode $end
$var wire 1 ( rst $end
$var wire 1 ) stall_pc $end
$var wire 32 , pc_out_0 [31:0] $end
$var wire 32 - pc_out [31:0] $end
$var wire 32 . pc_in [31:0] $end
$var wire 32 / pc_fetch [31:0] $end
$var wire 32 0 instr_fetch [31:0] $end
$scope module adder $end
$var wire 32 1 b [31:0] $end
$var wire 32 2 sum [31:0] $end
$var wire 32 3 a [31:0] $end
$upscope $end
$scope module imem $end
$var wire 32 4 instr [31:0] $end
$var wire 32 5 pc [31:0] $end
$upscope $end
$scope module pc $end
$var wire 1 # clk $end
$var wire 1 ( rst $end
$var wire 1 ) stall_pc $end
$var wire 32 6 pc_in [31:0] $end
$var reg 32 7 pc_out [31:0] $end
$upscope $end
$scope module select_branch $end
$var wire 32 8 a [31:0] $end
$var wire 32 9 b [31:0] $end
$var wire 1 ' sel $end
$var wire 32 : out [31:0] $end
$upscope $end
$scope module select_jump $end
$var wire 32 ; a [31:0] $end
$var wire 32 < b [31:0] $end
$var wire 1 $ sel $end
$var wire 32 = out [31:0] $end
$upscope $end
$upscope $end
$upscope $end
$enddefinitions $end
#0
$dumpvars
bx =
b0 <
bx ;
bx :
b0 9
bx 8
bx 7
bx 6
bx 5
bx 4
bx 3
bx 2
b100 1
bx 0
bx /
bx .
bx -
bx ,
b0 +
b0 *
0)
1(
0'
b0 &
b0 %
0$
0#
bx "
bx !
$end
#3000
0(
#5000
b100 .
b100 6
b100 =
b100000000000100000000000000101 "
b100000000000100000000000000101 0
b100000000000100000000000000101 4
b100 ,
b100 :
b100 ;
b100 !
b100 /
b100 2
b100 8
b0 -
b0 3
b0 5
b0 7
1#
#10000
0#
#13000
1(
#15000
b1000 .
b1000 6
b1000 =
b100000000000110000000000001100 "
b100000000000110000000000001100 0
b100000000000110000000000001100 4
b1000 ,
b1000 :
b1000 ;
b1000 !
b1000 /
b1000 2
b1000 8
b100 -
b100 3
b100 5
b100 7
1#
#20000
0#
#25000
b1100 .
b1100 6
b1100 =
b100000000001110000000000000110 "
b100000000001110000000000000110 0
b100000000001110000000000000110 4
b1100 ,
b1100 :
b1100 ;
b1100 !
b1100 /
b1100 2
b1100 8
b1000 -
b1000 3
b1000 5
b1000 7
1#
#30000
0#
#33000
1)
#35000
1#
#40000
0#
#43000
b100000 .
b100000 6
b100000 =
b100000 ,
b100000 :
b100000 ;
b100000 %
b100000 *
b100000 9
1'
0)
#45000
b10101100000001000000000000000100 "
b10101100000001000000000000000100 0
b10101100000001000000000000000100 4
b100100 !
b100100 /
b100100 2
b100100 8
b100000 -
b100000 3
b100000 5
b100000 7
1#
#50000
0#
#53000
b10000000 .
b10000000 6
b10000000 =
b100100 ,
b100100 :
b100100 ;
b10000000 &
b10000000 +
b10000000 <
1$
0'
#55000
bx "
bx 0
bx 4
b10000100 ,
b10000100 :
b10000100 ;
b10000100 !
b10000100 /
b10000100 2
b10000100 8
b10000000 -
b10000000 3
b10000000 5
b10000000 7
1#
#60000
0#
#63000
b10000100 .
b10000100 6
b10000100 =
0$
#65000
b10001000 .
b10001000 6
b10001000 =
b10001000 ,
b10001000 :
b10001000 ;
b10001000 !
b10001000 /
b10001000 2
b10001000 8
b10000100 -
b10000100 3
b10000100 5
b10000100 7
1#
#70000
0#
#75000
b10001100 .
b10001100 6
b10001100 =
b10001100 ,
b10001100 :
b10001100 ;
b10001100 !
b10001100 /
b10001100 2
b10001100 8
b10001000 -
b10001000 3
b10001000 5
b10001000 7
1#
