RTL/defines.v
`define WIDTH 32

//Opcode for Instructions

// R-Type
`define R_op 6'b000000

// I-Type
`define lw_op   6'b100011 
`define sw_op   6'b101011
`define addi_op 6'b001000
`define andi_op 6'b001100
`define ori_op  6'b001101
`define slti_op 6'b001010
`define beq_op  6'b000100
`define bne_op  6'b000101

// J-Type
`define jump_op    6'b000010

// Function for R-type
`define add_funct 6'b100000
`define sub_funct 6'b100010
`define and_funct 6'b100100
`define or_funct  6'b100101
`define slt_funct 6'b101010
`define nor_funct 6'b100111
`define sll_funct 6'b000000
`define srl_funct 6'b000010

// ALUControl
`define EXE_ADD 4'b0000
`define EXE_AND 4'b0001
`define EXE_SUB 4'b0010
`define EXE_OR 4'b0011
`define EXE_SLT 4'b0100 
`define EXE_NOR 4'b0101 
`define EXE_SLL 4'b0110 
`define EXE_SRL 4'b0111 
`define EXE_NO_OPERATION 4'b1111

// Using for control 
`define R_control     7'b1000100
`define lw_control    7'b1101000
`define sw_control    7'b0011000
`define addi_control  7'b1001000
`define andi_control  7'b1001000
`define ori_control   7'b1001000
`define slti_control  7'b1001000
`define beq_control   7'b0000001
`define bne_control   7'b0000001
`define jump_control  7'b0000010

// Using for branch condition
`define beq 2'b11
`define bne 2'b01
`define not_branch 2'b00

RTL/Memory/IMEM.v
`include "defines.v"

module IMEM (
  input [`WIDTH-1:0] pc,
  output [`WIDTH-1:0] instr
);

  // Memory
  reg [`WIDTH-1:0] instr_memory [31:0];

  initial begin
    $readmemh("Verification/instrMem.txt", instr_memory);;
  end

  assign instr = instr_memory[pc[`WIDTH-1:2]]; // 4 byte aligned

endmodule

Verification/IMEM_tb.v
`timescale 1ns/1ps
`include "defines.v"

module tb_imem;

  // Inputs
  reg [`WIDTH-1:0] pc;

  // Outputs
  wire [`WIDTH-1:0] instr;

  // Instantiate the Unit Under Test (UUT)
  IMEM uut (
    .pc(pc),
    .instr(instr)
  );

  // Dump waveforms
  initial begin
    $dumpfile("imem_test.vcd");
    $dumpvars(0, tb_imem);
  end

  // Test logic
  initial begin
    $display("===== BẮT ĐẦU TEST IMEM =====");

    // Khởi tạo PC
    pc = 0;

    // Đợi 10ns để nạp instrMem.txt
    #10;

    // In thử các lệnh đã nạp
    repeat (10) begin
      $display("PC = %0h | instr = %0h", pc, instr);
      pc = pc + 4;   // Mỗi lệnh cách nhau 4 byte
      #10;
    end

    $display("===== KẾT THÚC TEST =====");
    $finish;
  end

endmodule

imem_test.vcd
$date
	Sun May 18 17:27:47 2025
$end
$version
	Icarus Verilog
$end
$timescale
	1ps
$end
$scope module tb_imem $end
$var wire 32 ! instr [31:0] $end
$var reg 32 " pc [31:0] $end
$scope module uut $end
$var wire 32 # instr [31:0] $end
$var wire 32 $ pc [31:0] $end
$upscope $end
$upscope $end
$enddefinitions $end
#0
$dumpvars
b0 $
b100000000000100000000000000101 #
b0 "
b100000000000100000000000000101 !
$end
#10000
b100000000000110000000000001100 !
b100000000000110000000000001100 #
b100 "
b100 $
#20000
b100000000001110000000000000110 !
b100000000001110000000000000110 #
b1000 "
b1000 $
#30000
b100000000001000000000000000111 !
b100000000001000000000000000111 #
b1100 "
b1100 $
#40000
b11000100011000000100010 !
b11000100011000000100010 #
b10000 "
b10000 $
#50000
b1110010100011000000 !
b1110010100011000000 #
b10100 "
b10100 $
#60000
b101001000100000000100010 !
b101001000100000000100010 #
b11000 "
b11000 $
#70000
b10001100010100000100100 !
b10001100010100000100100 #
b11100 "
b11100 $
#80000
b10101100000001000000000000000100 !
b10101100000001000000000000000100 #
b100000 "
b100000 $
#90000
b10001100000000100000000000000100 !
b10001100000000100000000000000100 #
b100100 "
b100100 $
#100000
b1000000100101000000100010 !
b1000000100101000000100010 #
b101000 "
b101000 $
