RTL/defines.v
`define WIDTH 32

//Opcode for Instructions

// R-Type
`define R_op 6'b000000

// I-Type
`define lw_op   6'b100011 
`define sw_op   6'b101011
`define addi_op 6'b001000
`define andi_op 6'b001100
`define ori_op  6'b001101
`define slti_op 6'b001010
`define beq_op  6'b000100
`define bne_op  6'b000101

// J-Type
`define jump_op    6'b000010

// Function for R-type
`define add_funct 6'b100000
`define sub_funct 6'b100010
`define and_funct 6'b100100
`define or_funct  6'b100101
`define slt_funct 6'b101010
`define nor_funct 6'b100111
`define sll_funct 6'b000000
`define srl_funct 6'b000010

// ALUControl
`define EXE_ADD 4'b0000
`define EXE_AND 4'b0001
`define EXE_SUB 4'b0010
`define EXE_OR 4'b0011
`define EXE_SLT 4'b0100 
`define EXE_NOR 4'b0101 
`define EXE_SLL 4'b0110 
`define EXE_SRL 4'b0111 
`define EXE_NO_OPERATION 4'b1111

// Using for control 
`define R_control     7'b1000100
`define lw_control    7'b1101000
`define sw_control    7'b0011000
`define addi_control  7'b1001000
`define andi_control  7'b1001000
`define ori_control   7'b1001000
`define slti_control  7'b1001000
`define beq_control   7'b0000001
`define bne_control   7'b0000001
`define jump_control  7'b0000010

// Using for branch condition
`define beq 2'b11
`define bne 2'b01
`define not_branch 2'b00

RTL/pc.v
`include "defines.v"

module pc(
  input clk, rst,
  input stall_pc,
  input [`WIDTH-1:0] pc_in,
  output reg [`WIDTH-1:0] pc_out
);

  always @(posedge clk) begin
    if(!rst) begin
      pc_out <= 0; // Reset the PC to 0
    end
    else if (stall_pc) begin
      pc_out <= pc_out; // Hold the value if stalled
    end
    else begin
      pc_out <= pc_in; // Update the PC with the new value
    end
  end

endmodule

Verification/pc_tb.v
`timescale 1ns/1ps

module pc_tb;

  reg clk, rst, stall_pc;
  reg [31:0] pc_in;
  wire [31:0] pc_out;

  // Instantiate the PC module
  pc dut (
    .clk(clk),
    .rst(rst),
    .stall_pc(stall_pc),
    .pc_in(pc_in),
    .pc_out(pc_out)
  );

  // Clock generation
  initial begin
    clk = 0;
    forever #5 clk = ~clk; // 10ns period
  end

  // Print values to console at every positive clock edge
  always @(posedge clk) begin
    $display("Time %0t ns: pc_in = %h, pc_out = %h, stall_pc = %b, rst = %b", $time, pc_in, pc_out, stall_pc, rst);
  end

  // Stimulus
  initial begin
    // Dump waveform
    $dumpfile("pc.vcd");
    $dumpvars(0, pc_tb);

    // Initialize signals
    rst = 1;
    stall_pc = 0;
    pc_in = 0;

    // Apply reset
    #3 rst = 0;
    #10 rst = 1;

    // Test 1: Normal increment
    #10 pc_in = 32'h00000004;
    #10 pc_in = 32'h00000008;
    #10 pc_in = 32'h0000000C;

    // Test 2: Stall the PC
    stall_pc = 1;
    pc_in = 32'h00000010;
    #10; // PC should not change
    #10;

    // Remove stall
    stall_pc = 0;
    pc_in = 32'h00000014;
    #10;
    
    #20;

    // Finish simulation
    $finish;
  end

endmodule

pc.vcd
$date
	Sun May 18 18:31:01 2025
$end
$version
	Icarus Verilog
$end
$timescale
	1ps
$end
$scope module pc_tb $end
$var wire 32 ! pc_out [31:0] $end
$var reg 1 " clk $end
$var reg 32 # pc_in [31:0] $end
$var reg 1 $ rst $end
$var reg 1 % stall_pc $end
$scope module dut $end
$var wire 1 " clk $end
$var wire 32 & pc_in [31:0] $end
$var wire 1 $ rst $end
$var wire 1 % stall_pc $end
$var reg 32 ' pc_out [31:0] $end
$upscope $end
$upscope $end
$enddefinitions $end
#0
$dumpvars
bx '
b0 &
0%
1$
b0 #
0"
bx !
$end
#3000
0$
#5000
b0 !
b0 '
1"
#10000
0"
#13000
1$
#15000
1"
#20000
0"
#23000
b100 #
b100 &
#25000
b100 !
b100 '
1"
#30000
0"
#33000
b1000 #
b1000 &
#35000
b1000 !
b1000 '
1"
#40000
0"
#43000
1%
b10000 #
b10000 &
#45000
1"
#50000
0"
#55000
1"
#60000
0"
#63000
b10100 #
b10100 &
0%
#65000
b10100 !
b10100 '
1"
